spicyid/__init__.py
spicyid/generate_random_strings.py
spicyid/generate_spicy_id.py
spicyid/generate_timestamp_value.py
spicyid/get_object_values.py
spicyid/spicy_id.py
spicyid/utils/__init__.py
spicyid/utils/logger.py
spicyid-1.0.1.dist-info/LICENSE.md
spicyid-1.0.1.dist-info/METADATA
spicyid-1.0.1.dist-info/WHEEL
spicyid-1.0.1.dist-info/top_level.txt
spicyid-1.0.1.dist-info/RECORD
