Metadata-Version: 2.1
Name: spicyid
Version: 1.0.1
Summary: A simple Python package
Home-page: https://github.com/DarkestAbed/python-spicyids
Author: The Darkest Abed
Author-email: thedarkestabed@gmail.com
Project-URL: Bug Tracker, https://github.com/DarkestAbed/python-spicyids/issues
Project-URL: repository, https://github.com/DarkestAbed/python-spicyids
Classifier: Programming Language :: Python :: 3
Classifier: Operating System :: OS Independent
Classifier: License :: OSI Approved :: The Unlicense (Unlicense)
Requires-Python: >=3.12
License-File: LICENSE.md
